LICENSE.txt
README.md
setup.cfg
setup.py
saranphat/Saranphat.py
saranphat/__init__.py
saranphat.egg-info/PKG-INFO
saranphat.egg-info/SOURCES.txt
saranphat.egg-info/dependency_links.txt
saranphat.egg-info/top_level.txt